{
  "project_info": {
    "project_number": "911588427998",
    "project_id": "utcazene-3537d",
    "storage_bucket": "utcazene-3537d.appspot.com"
  },
  "client": [
    {
      "client_info": {
        "mobilesdk_app_id": "1:911588427998:android:9467b3a115e5566c9f9a4f",
        "android_client_info": {
          "package_name": "com.csakitheone.streetmusic"
        }
      },
      "oauth_client": [
        {
          "client_id": "911588427998-i8nb4epsblh8gkkasi61fgojtkak5315.apps.googleusercontent.com",
          "client_type": 1,
          "android_info": {
            "package_name": "com.csakitheone.streetmusic",
            "certificate_hash": "273666be55c9d9fa44488e70489ea0d36e9b0553"
          }
        },
        {
          "client_id": "911588427998-ruoqc4ksf2ceddtmu20igk6ejnq3r4i6.apps.googleusercontent.com",
          "client_type": 1,
          "android_info": {
            "package_name": "com.csakitheone.streetmusic",
            "certificate_hash": "05c898a44e78a22ad83bf783514f4ce49804364e"
          }
        },
        {
          "client_id": "911588427998-8q813ugsd2ge9q8r31kgpq9h8i3sff74.apps.googleusercontent.com",
          "client_type": 3
        }
      ],
      "api_key": [
        {
          "current_key": "AIzaSyD51mhUmrjZDnqGviKPsK3v1NQA6rbFim8"
        }
      ],
      "services": {
        "appinvite_service": {
          "other_platform_oauth_client": [
            {
              "client_id": "911588427998-8q813ugsd2ge9q8r31kgpq9h8i3sff74.apps.googleusercontent.com",
              "client_type": 3
            }
          ]
        }
      }
    }
  ],
  "configuration_version": "1"
}